jwt_django/__init__.py
jwt_django/core.py
jwt_django/ktoken.cp37-win32.pyd
jwt_django-1.2.dist-info/METADATA
jwt_django-1.2.dist-info/WHEEL
jwt_django-1.2.dist-info/top_level.txt
jwt_django-1.2.dist-info/RECORD
