Metadata-Version: 2.1
Name: jwt-django
Version: 1.2
Summary: Provide end-to-end control jwt token (Simple & Easy to Use)
Author: Momin Iqbal (Pakistan Dedov)
Author-email: <mominiqbal1214@gmail.com>
Keywords: python,django,jwt,jwt for django,jwt for django,jwt_django,django_jwt
Classifier: Development Status :: 1 - Planning
Classifier: Intended Audience :: Developers
Classifier: Programming Language :: Python :: 3
Classifier: Operating System :: Unix
Classifier: Operating System :: MacOS :: MacOS X
Classifier: Operating System :: Microsoft :: Windows
Requires-Dist: django
Requires-Dist: djangorestframework
Requires-Dist: PyJWT
